signal_separation/SVRh
signal_separation/SVRp
signal_separation/__init__.py
signal_separation/_evaluation.py
signal_separation/_file_downloader.py
signal_separation/_genetic_alg.py
signal_separation/_neural_network.py
signal_separation/_signal_creator.py
signal_separation/neural_network.h5
signal_separation-0.0.15.dist-info/LICENSE.txt
signal_separation-0.0.15.dist-info/METADATA
signal_separation-0.0.15.dist-info/WHEEL
signal_separation-0.0.15.dist-info/top_level.txt
signal_separation-0.0.15.dist-info/RECORD
