Metadata-Version: 2.1
Name: signal-separation
Version: 0.0.15
Summary: Algorithm for generating and separating analytical chemistry signal.
Home-page: https://github.com/MieszkoP
Author: Mieszko Pasierbek
Author-email: mieszko.pasierbek@gmail.com
License: MIT
Download-URL: https://github.com/MieszkoP/signal_separation/archive/refs/tags/0.0.15.tar.gz
Keywords: CNN,Deep Learning,signal,SVR,chemometrics,chemistry
Platform: UNKNOWN
Classifier: Development Status :: 4 - Beta
Classifier: Intended Audience :: Developers
Classifier: Topic :: Software Development :: Build Tools
Classifier: License :: OSI Approved :: MIT License
Classifier: Programming Language :: Python :: 3
Classifier: Programming Language :: Python :: 3.4
Classifier: Programming Language :: Python :: 3.5
Classifier: Programming Language :: Python :: 3.6
Classifier: Programming Language :: Python :: 3.7
License-File: LICENSE.txt
Requires-Dist: numpy
Requires-Dist: tensorflow
